{"dataset": "StarLightCurves", "depth": 9, "nb_filters": 32, "batch_size": 16, "kernel_size": 41, "use_residual": "False", "use_bottleneck": "True", "acc": 0.9785089849441476, "precision": 0.973656806556973, "recall": 0.9631482021566202, "budget_ran": 1500, "duration": 3548.4397127628326}
{"dataset": "StarLightCurves", "depth": 9, "nb_filters": 64, "batch_size": 16, "kernel_size": 32, "use_residual": "True", "use_bottleneck": "False", "acc": 0.975594949004371, "precision": 0.9685829388289872, "recall": 0.9598992854706413, "budget_ran": 1500, "duration": 4388.254323244095}
{"dataset": "StarLightCurves", "depth": 9, "nb_filters": 64, "batch_size": 16, "kernel_size": 32, "use_residual": "False", "use_bottleneck": "True", "acc": 0.9774162214667315, "precision": 0.9713501520054919, "recall": 0.9625171546177057, "budget_ran": 1500, "duration": 4407.796504020691}
{"dataset": "StarLightCurves", "depth": 3, "nb_filters": 32, "batch_size": 32, "kernel_size": 64, "use_residual": "True", "use_bottleneck": "True", "acc": 0.9757163671685284, "precision": 0.9700506478611827, "recall": 0.9584136794172653, "budget_ran": 1500, "duration": 849.8936293125153}
{"dataset": "StarLightCurves", "depth": 9, "nb_filters": 32, "batch_size": 32, "kernel_size": 41, "use_residual": "True", "use_bottleneck": "False", "acc": 0.9760806216610005, "precision": 0.9721943986762746, "recall": 0.9574840843429696, "budget_ran": 1500, "duration": 2360.82048535347}
{"dataset": "StarLightCurves", "depth": 6, "nb_filters": 64, "batch_size": 128, "kernel_size": 41, "use_residual": "False", "use_bottleneck": "False", "acc": 0.9776590577950461, "precision": 0.9736696120282198, "recall": 0.9606009891960179, "budget_ran": 1500, "duration": 2191.0363295078278}
{"dataset": "StarLightCurves", "depth": 6, "nb_filters": 64, "batch_size": 32, "kernel_size": 41, "use_residual": "False", "use_bottleneck": "False", "acc": 0.9771733851384167, "precision": 0.9721688796428417, "recall": 0.9610238880798766, "budget_ran": 1500, "duration": 2477.258965730667}
{"dataset": "StarLightCurves", "depth": 9, "nb_filters": 64, "batch_size": 128, "kernel_size": 64, "use_residual": "False", "use_bottleneck": "False", "acc": 0.9783875667799903, "precision": 0.9743567639895202, "recall": 0.9618740455451736, "budget_ran": 1500, "duration": 3627.957807302475}
{"dataset": "StarLightCurves", "depth": 6, "nb_filters": 64, "batch_size": 32, "kernel_size": 41, "use_residual": "False", "use_bottleneck": "True", "acc": 0.9764448761534725, "precision": 0.9707794737264431, "recall": 0.9600384179947756, "budget_ran": 1500, "duration": 2481.5001168251038}
{"dataset": "StarLightCurves", "depth": 6, "nb_filters": 32, "batch_size": 32, "kernel_size": 64, "use_residual": "False", "use_bottleneck": "False", "acc": 0.9796017484215639, "precision": 0.9746086835560613, "recall": 0.965483965675293, "budget_ran": 1500, "duration": 1583.0318212509155}
{"dataset": "StarLightCurves", "depth": 3, "nb_filters": 16, "batch_size": 128, "kernel_size": 41, "use_residual": "True", "use_bottleneck": "True", "acc": 0.9775376396308888, "precision": 0.9719364074198342, "recall": 0.9622355887825637, "budget_ran": 1500, "duration": 383.6243140697479}
{"dataset": "StarLightCurves", "depth": 3, "nb_filters": 16, "batch_size": 64, "kernel_size": 32, "use_residual": "True", "use_bottleneck": "True", "acc": 0.9757163671685284, "precision": 0.9763767354593377, "recall": 0.9520209944931715, "budget_ran": 1500, "duration": 434.0191261768341}
{"dataset": "StarLightCurves", "depth": 3, "nb_filters": 64, "batch_size": 64, "kernel_size": 64, "use_residual": "True", "use_bottleneck": "True", "acc": 0.9766877124817873, "precision": 0.9784607293150339, "recall": 0.9531466973646979, "budget_ran": 1500, "duration": 1011.5057673454285}
{"dataset": "StarLightCurves", "depth": 3, "nb_filters": 16, "batch_size": 64, "kernel_size": 64, "use_residual": "True", "use_bottleneck": "True", "acc": 0.975594949004371, "precision": 0.9681489812014004, "recall": 0.9598351895063412, "budget_ran": 1500, "duration": 503.7076635360718}
{"dataset": "StarLightCurves", "depth": 9, "nb_filters": 64, "batch_size": 64, "kernel_size": 32, "use_residual": "True", "use_bottleneck": "True", "acc": 0.9758377853326857, "precision": 0.968499352900602, "recall": 0.960540194018591, "budget_ran": 1500, "duration": 3086.914594888687}
{"dataset": "StarLightCurves", "depth": 9, "nb_filters": 16, "batch_size": 128, "kernel_size": 64, "use_residual": "False", "use_bottleneck": "False", "acc": 0.9771733851384167, "precision": 0.9715306535993036, "recall": 0.9611728816130464, "budget_ran": 1500, "duration": 1193.7582297325134}
{"dataset": "StarLightCurves", "depth": 3, "nb_filters": 16, "batch_size": 16, "kernel_size": 32, "use_residual": "True", "use_bottleneck": "True", "acc": 0.9748664400194269, "precision": 0.9669699895629696, "recall": 0.959201401649595, "budget_ran": 1500, "duration": 1341.6943895816803}
{"dataset": "StarLightCurves", "depth": 3, "nb_filters": 64, "batch_size": 16, "kernel_size": 64, "use_residual": "True", "use_bottleneck": "True", "acc": 0.976930548810102, "precision": 0.971588884589775, "recall": 0.9607450625625661, "budget_ran": 1500, "duration": 1675.0649154186249}
{"dataset": "StarLightCurves", "depth": 3, "nb_filters": 16, "batch_size": 16, "kernel_size": 41, "use_residual": "True", "use_bottleneck": "True", "acc": 0.9765662943176299, "precision": 0.9752205790431298, "recall": 0.955420565443653, "budget_ran": 1500, "duration": 1327.9287316799164}
{"dataset": "StarLightCurves", "depth": 3, "nb_filters": 16, "batch_size": 16, "kernel_size": 64, "use_residual": "True", "use_bottleneck": "True", "acc": 0.9785089849441476, "precision": 0.9738854462697257, "recall": 0.9632867948875052, "budget_ran": 1500, "duration": 1406.7465341091156}
{"dataset": "StarLightCurves", "depth": 6, "nb_filters": 16, "batch_size": 16, "kernel_size": 32, "use_residual": "True", "use_bottleneck": "True", "acc": 0.9759592034968432, "precision": 0.9701289541926398, "recall": 0.9587670017011605, "budget_ran": 1500, "duration": 2207.6045212745667}
{"dataset": "StarLightCurves", "depth": 6, "nb_filters": 16, "batch_size": 16, "kernel_size": 41, "use_residual": "True", "use_bottleneck": "True", "acc": 0.9798445847498786, "precision": 0.9771973549659156, "recall": 0.9635678002536056, "budget_ran": 1500, "duration": 2221.5825004577637}
{"dataset": "StarLightCurves", "depth": 9, "nb_filters": 32, "batch_size": 128, "kernel_size": 32, "use_residual": "False", "use_bottleneck": "False", "acc": 0.9775376396308888, "precision": 0.9743144331069787, "recall": 0.9592523358179865, "budget_ran": 1500, "duration": 1527.05237865448}
{"dataset": "StarLightCurves", "depth": 3, "nb_filters": 32, "batch_size": 128, "kernel_size": 64, "use_residual": "True", "use_bottleneck": "True", "acc": 0.9788732394366197, "precision": 0.9758488777168757, "recall": 0.9619414216205545, "budget_ran": 1500, "duration": 500.6152677536011}
{"dataset": "StarLightCurves", "depth": 9, "nb_filters": 32, "batch_size": 64, "kernel_size": 41, "use_residual": "True", "use_bottleneck": "True", "acc": 0.978630403108305, "precision": 0.9761821308565884, "recall": 0.9608743340776652, "budget_ran": 1500, "duration": 1887.3399608135223}
{"dataset": "StarLightCurves", "depth": 9, "nb_filters": 64, "batch_size": 32, "kernel_size": 64, "use_residual": "True", "use_bottleneck": "True", "acc": 0.9768091306459447, "precision": 0.9691459664776133, "recall": 0.9630189306415211, "budget_ran": 1500, "duration": 3867.082663536072}
{"dataset": "StarLightCurves", "depth": 9, "nb_filters": 32, "batch_size": 64, "kernel_size": 64, "use_residual": "True", "use_bottleneck": "True", "acc": 0.9776590577950461, "precision": 0.9706878573882131, "recall": 0.9639359243889499, "budget_ran": 1500, "duration": 1894.5390343666077}
{"dataset": "StarLightCurves", "depth": 3, "nb_filters": 16, "batch_size": 32, "kernel_size": 32, "use_residual": "False", "use_bottleneck": "True", "acc": 0.9747450218552696, "precision": 0.9674389593383116, "recall": 0.958278927266503, "budget_ran": 1500, "duration": 690.1921970844269}
{"dataset": "StarLightCurves", "depth": 9, "nb_filters": 16, "batch_size": 32, "kernel_size": 64, "use_residual": "True", "use_bottleneck": "True", "acc": 0.9774162214667315, "precision": 0.9721841156588016, "recall": 0.9615902998612417, "budget_ran": 1500, "duration": 1962.5511198043823}
{"dataset": "StarLightCurves", "depth": 9, "nb_filters": 16, "batch_size": 128, "kernel_size": 32, "use_residual": "False", "use_bottleneck": "False", "acc": 0.9749878581835842, "precision": 0.971537355262026, "recall": 0.9543704596010024, "budget_ran": 1500, "duration": 1009.0002987384796}
{"dataset": "StarLightCurves", "depth": 3, "nb_filters": 32, "batch_size": 64, "kernel_size": 32, "use_residual": "False", "use_bottleneck": "False", "acc": 0.9768091306459447, "precision": 0.9731208281903484, "recall": 0.9582668657328854, "budget_ran": 1500, "duration": 544.3562326431274}
{"dataset": "StarLightCurves", "depth": 9, "nb_filters": 64, "batch_size": 128, "kernel_size": 32, "use_residual": "True", "use_bottleneck": "True", "acc": 0.9762020398251579, "precision": 0.9715976242081071, "recall": 0.9583320619594767, "budget_ran": 1500, "duration": 2967.332756280899}
{"dataset": "StarLightCurves", "depth": 3, "nb_filters": 64, "batch_size": 64, "kernel_size": 41, "use_residual": "False", "use_bottleneck": "False", "acc": 0.9630888780961632, "precision": 0.9387967504634055, "recall": 0.9591444786604084, "budget_ran": 1500, "duration": 920.9253845214844}
{"dataset": "StarLightCurves", "depth": 9, "nb_filters": 32, "batch_size": 16, "kernel_size": 64, "use_residual": "True", "use_bottleneck": "True", "acc": 0.9781447304516756, "precision": 0.9711119798336547, "recall": 0.9650687479516801, "budget_ran": 1500, "duration": 3627.251000881195}
{"dataset": "StarLightCurves", "depth": 3, "nb_filters": 64, "batch_size": 32, "kernel_size": 32, "use_residual": "True", "use_bottleneck": "True", "acc": 0.9743807673627974, "precision": 0.9656984722440006, "recall": 0.9591340255742139, "budget_ran": 1500, "duration": 1083.2635338306427}
{"dataset": "StarLightCurves", "depth": 3, "nb_filters": 64, "batch_size": 16, "kernel_size": 41, "use_residual": "True", "use_bottleneck": "True", "acc": 0.9725594949004371, "precision": 0.9688503369596798, "recall": 0.9501234715030556, "budget_ran": 1500, "duration": 1644.1107249259949}
{"dataset": "StarLightCurves", "depth": 3, "nb_filters": 32, "batch_size": 32, "kernel_size": 32, "use_residual": "True", "use_bottleneck": "True", "acc": 0.975230694511899, "precision": 0.974056591399996, "recall": 0.9527314796410846, "budget_ran": 1500, "duration": 803.6811485290527}
{"dataset": "StarLightCurves", "depth": 9, "nb_filters": 16, "batch_size": 64, "kernel_size": 41, "use_residual": "False", "use_bottleneck": "False", "acc": 0.9776590577950461, "precision": 0.9736566192722839, "recall": 0.9605264924294331, "budget_ran": 1500, "duration": 1370.8420028686523}
{"dataset": "StarLightCurves", "depth": 3, "nb_filters": 64, "batch_size": 128, "kernel_size": 64, "use_residual": "True", "use_bottleneck": "True", "acc": 0.9771733851384167, "precision": 0.9773140972449049, "recall": 0.9554194651813618, "budget_ran": 1500, "duration": 908.4913206100464}
{"dataset": "StarLightCurves", "depth": 9, "nb_filters": 32, "batch_size": 128, "kernel_size": 41, "use_residual": "True", "use_bottleneck": "True", "acc": 0.9775376396308888, "precision": 0.9741232444978092, "recall": 0.9596040180463413, "budget_ran": 1500, "duration": 1642.040409564972}
{"dataset": "StarLightCurves", "depth": 9, "nb_filters": 64, "batch_size": 64, "kernel_size": 64, "use_residual": "False", "use_bottleneck": "False", "acc": 0.977294803302574, "precision": 0.969190916667574, "recall": 0.964364843701721, "budget_ran": 1500, "duration": 3387.166018486023}
{"dataset": "StarLightCurves", "depth": 3, "nb_filters": 32, "batch_size": 16, "kernel_size": 32, "use_residual": "True", "use_bottleneck": "False", "acc": 0.9774162214667315, "precision": 0.9768180020936067, "recall": 0.9567637381860212, "budget_ran": 1500, "duration": 1319.8377013206482}
{"dataset": "StarLightCurves", "depth": 3, "nb_filters": 64, "batch_size": 128, "kernel_size": 32, "use_residual": "False", "use_bottleneck": "False", "acc": 0.9791160757649344, "precision": 0.9775618873575395, "recall": 0.9609417101530463, "budget_ran": 1500, "duration": 812.9863698482513}
{"dataset": "StarLightCurves", "depth": 9, "nb_filters": 64, "batch_size": 16, "kernel_size": 64, "use_residual": "False", "use_bottleneck": "False", "acc": 0.9779018941233608, "precision": 0.9716006556688694, "recall": 0.963436888682966, "budget_ran": 1500, "duration": 4887.500734567642}
{"dataset": "StarLightCurves", "depth": 3, "nb_filters": 32, "batch_size": 64, "kernel_size": 64, "use_residual": "False", "use_bottleneck": "False", "acc": 0.9738950947061681, "precision": 0.9616990437567768, "recall": 0.9621884951942947, "budget_ran": 1500, "duration": 586.9313151836395}
{"dataset": "StarLightCurves", "depth": 6, "nb_filters": 16, "batch_size": 16, "kernel_size": 64, "use_residual": "True", "use_bottleneck": "True", "acc": 0.9783875667799903, "precision": 0.9701461719102009, "recall": 0.9666365112560937, "budget_ran": 1500, "duration": 2375.6797144412994}
{"dataset": "StarLightCurves", "depth": 3, "nb_filters": 16, "batch_size": 128, "kernel_size": 64, "use_residual": "True", "use_bottleneck": "True", "acc": 0.978630403108305, "precision": 0.9781101957059174, "recall": 0.9590310253670219, "budget_ran": 1500, "duration": 356.2172496318817}
{"dataset": "StarLightCurves", "depth": 3, "nb_filters": 32, "batch_size": 128, "kernel_size": 32, "use_residual": "True", "use_bottleneck": "True", "acc": 0.975594949004371, "precision": 0.9706791099938924, "recall": 0.9572036187701188, "budget_ran": 1500, "duration": 454.12213706970215}
{"dataset": "StarLightCurves", "depth": 9, "nb_filters": 16, "batch_size": 16, "kernel_size": 32, "use_residual": "True", "use_bottleneck": "True", "acc": 0.9728023312287518, "precision": 0.9643405895141989, "recall": 0.9556654384928107, "budget_ran": 1500, "duration": 3207.037118434906}
{"dataset": "StarLightCurves", "depth": 9, "nb_filters": 16, "batch_size": 32, "kernel_size": 41, "use_residual": "True", "use_bottleneck": "False", "acc": 0.9781447304516756, "precision": 0.973988610963972, "recall": 0.9615207232612782, "budget_ran": 1500, "duration": 1947.8532021045685}
{"dataset": "StarLightCurves", "depth": 3, "nb_filters": 64, "batch_size": 64, "kernel_size": 32, "use_residual": "False", "use_bottleneck": "False", "acc": 0.9774162214667315, "precision": 0.9756443021609691, "recall": 0.9576160961759004, "budget_ran": 1500, "duration": 923.6880571842194}
{"dataset": "StarLightCurves", "depth": 3, "nb_filters": 64, "batch_size": 32, "kernel_size": 64, "use_residual": "False", "use_bottleneck": "False", "acc": 0.9758377853326857, "precision": 0.9702157680056147, "recall": 0.9586223885413631, "budget_ran": 1500, "duration": 1223.871245622635}
{"dataset": "StarLightCurves", "depth": 9, "nb_filters": 16, "batch_size": 64, "kernel_size": 64, "use_residual": "False", "use_bottleneck": "False", "acc": 0.976930548810102, "precision": 0.971810688390261, "recall": 0.9601802908367416, "budget_ran": 1500, "duration": 1407.3472640514374}
{"dataset": "StarLightCurves", "depth": 9, "nb_filters": 16, "batch_size": 64, "kernel_size": 32, "use_residual": "False", "use_bottleneck": "False", "acc": 0.9762020398251579, "precision": 0.9700061654592674, "recall": 0.9601112747058199, "budget_ran": 1500, "duration": 1287.5344676971436}
{"dataset": "StarLightCurves", "depth": 9, "nb_filters": 64, "batch_size": 32, "kernel_size": 32, "use_residual": "False", "use_bottleneck": "False", "acc": 0.9754735308402137, "precision": 0.9678817012144117, "recall": 0.9603298448389529, "budget_ran": 1500, "duration": 3507.645658969879}
{"dataset": "StarLightCurves", "depth": 9, "nb_filters": 32, "batch_size": 128, "kernel_size": 64, "use_residual": "False", "use_bottleneck": "False", "acc": 0.9776590577950461, "precision": 0.9728531622447174, "recall": 0.9612402576884272, "budget_ran": 1500, "duration": 1707.1482830047607}
{"dataset": "StarLightCurves", "depth": 3, "nb_filters": 16, "batch_size": 32, "kernel_size": 64, "use_residual": "False", "use_bottleneck": "False", "acc": 0.976930548810102, "precision": 0.9707787691250198, "recall": 0.9612457383240905, "budget_ran": 1500, "duration": 803.9244422912598}
{"dataset": "StarLightCurves", "depth": 9, "nb_filters": 32, "batch_size": 32, "kernel_size": 32, "use_residual": "False", "use_bottleneck": "False", "acc": 0.9779018941233608, "precision": 0.9725660586352354, "recall": 0.9624459379622018, "budget_ran": 1500, "duration": 2155.5044989585876}
{"dataset": "StarLightCurves", "depth": 3, "nb_filters": 32, "batch_size": 16, "kernel_size": 64, "use_residual": "False", "use_bottleneck": "False", "acc": 0.976930548810102, "precision": 0.973221415811173, "recall": 0.9586141675878682, "budget_ran": 1500, "duration": 1414.2245314121246}
{"dataset": "StarLightCurves", "depth": 3, "nb_filters": 64, "batch_size": 16, "kernel_size": 32, "use_residual": "False", "use_bottleneck": "False", "acc": 0.9734094220495386, "precision": 0.9663879617160475, "recall": 0.9551636624689953, "budget_ran": 1500, "duration": 1559.2762582302094}
{"dataset": "StarLightCurves", "depth": 3, "nb_filters": 32, "batch_size": 64, "kernel_size": 41, "use_residual": "False", "use_bottleneck": "False", "acc": 0.9753521126760564, "precision": 0.9709883516466732, "recall": 0.9562110279938141, "budget_ran": 1500, "duration": 575.1327881813049}
{"dataset": "StarLightCurves", "depth": 3, "nb_filters": 16, "batch_size": 128, "kernel_size": 32, "use_residual": "True", "use_bottleneck": "True", "acc": 0.9745021855269548, "precision": 0.9650224122195551, "recall": 0.9603336854190756, "budget_ran": 1500, "duration": 323.87716913223267}
{"dataset": "StarLightCurves", "depth": 3, "nb_filters": 16, "batch_size": 32, "kernel_size": 41, "use_residual": "False", "use_bottleneck": "True", "acc": 0.9768091306459447, "precision": 0.9741074557276729, "recall": 0.9573400109764215, "budget_ran": 1500, "duration": 742.5645697116852}
{"dataset": "StarLightCurves", "depth": 3, "nb_filters": 32, "batch_size": 16, "kernel_size": 41, "use_residual": "True", "use_bottleneck": "False", "acc": 0.9770519669742593, "precision": 0.9766591556942431, "recall": 0.9559141205139735, "budget_ran": 1500, "duration": 1368.112893819809}
{"dataset": "StarLightCurves", "depth": 3, "nb_filters": 32, "batch_size": 128, "kernel_size": 41, "use_residual": "False", "use_bottleneck": "False", "acc": 0.9777804759592035, "precision": 0.9759674671674411, "recall": 0.9586788033454177, "budget_ran": 1500, "duration": 503.9640598297119}
{"dataset": "StarLightCurves", "depth": 9, "nb_filters": 64, "batch_size": 64, "kernel_size": 41, "use_residual": "False", "use_bottleneck": "False", "acc": 0.9788732394366197, "precision": 0.974503925137889, "recall": 0.9633585513362584, "budget_ran": 1500, "duration": 3267.1458871364594}
{"dataset": "StarLightCurves", "depth": 9, "nb_filters": 64, "batch_size": 16, "kernel_size": 41, "use_residual": "False", "use_bottleneck": "False", "acc": 0.9779018941233608, "precision": 0.9707517190565867, "recall": 0.9647154256677847, "budget_ran": 1500, "duration": 4707.475297689438}
{"dataset": "StarLightCurves", "depth": 3, "nb_filters": 32, "batch_size": 32, "kernel_size": 41, "use_residual": "False", "use_bottleneck": "False", "acc": 0.9748664400194269, "precision": 0.9640216938138416, "recall": 0.9625363368425267, "budget_ran": 1500, "duration": 835.3702018260956}
{"dataset": "StarLightCurves", "depth": 9, "nb_filters": 32, "batch_size": 64, "kernel_size": 32, "use_residual": "True", "use_bottleneck": "False", "acc": 0.9764448761534725, "precision": 0.9699130869110636, "recall": 0.9607521832537698, "budget_ran": 1500, "duration": 1696.7176609039307}
{"dataset": "StarLightCurves", "depth": 3, "nb_filters": 16, "batch_size": 64, "kernel_size": 41, "use_residual": "False", "use_bottleneck": "False", "acc": 0.9787518212724624, "precision": 0.974280699573218, "recall": 0.9632884349430456, "budget_ran": 1500, "duration": 472.1541757583618}
{"dataset": "StarLightCurves", "depth": 9, "nb_filters": 16, "batch_size": 32, "kernel_size": 32, "use_residual": "True", "use_bottleneck": "True", "acc": 0.9777804759592035, "precision": 0.9734130258270346, "recall": 0.9612358773150552, "budget_ran": 1500, "duration": 1793.2183821201324}
{"dataset": "StarLightCurves", "depth": 9, "nb_filters": 16, "batch_size": 128, "kernel_size": 41, "use_residual": "True", "use_bottleneck": "False", "acc": 0.9804516755706654, "precision": 0.9810533334246521, "recall": 0.9617129904783863, "budget_ran": 1500, "duration": 1135.7359673976898}
{"dataset": "StarLightCurves", "depth": 9, "nb_filters": 32, "batch_size": 16, "kernel_size": 32, "use_residual": "True", "use_bottleneck": "True", "acc": 0.9788732394366197, "precision": 0.974919183064884, "recall": 0.9631454618387886, "budget_ran": 1500, "duration": 3288.0881860256195}
{"dataset": "StarLightCurves", "depth": 9, "nb_filters": 16, "batch_size": 16, "kernel_size": 41, "use_residual": "True", "use_bottleneck": "True", "acc": 0.9768091306459447, "precision": 0.9696837711877372, "recall": 0.9622410694182267, "budget_ran": 1500, "duration": 3123.483426809311}
{"dataset": "StarLightCurves", "depth": 9, "nb_filters": 16, "batch_size": 16, "kernel_size": 64, "use_residual": "True", "use_bottleneck": "True", "acc": 0.9764448761534725, "precision": 0.9696690757813928, "recall": 0.9609652727512396, "budget_ran": 1500, "duration": 3330.274489879608}
{"dataset": "StarLightCurves", "depth": 3, "nb_filters": 16, "batch_size": 32, "kernel_size": 32, "use_residual": "True", "use_bottleneck": "True", "acc": 0.976930548810102, "precision": 0.977405484317362, "recall": 0.954917149364297, "budget_ran": 1500, "duration": 699.401487827301}
{"dataset": "StarLightCurves", "depth": 3, "nb_filters": 16, "batch_size": 32, "kernel_size": 41, "use_residual": "True", "use_bottleneck": "True", "acc": 0.9780233122875183, "precision": 0.9773303120913437, "recall": 0.9576894926801941, "budget_ran": 1500, "duration": 743.8877348899841}
{"dataset": "StarLightCurves", "depth": 3, "nb_filters": 16, "batch_size": 32, "kernel_size": 64, "use_residual": "True", "use_bottleneck": "True", "acc": 0.9734094220495386, "precision": 0.960667755220394, "recall": 0.9620570231546134, "budget_ran": 1500, "duration": 750.6016235351562}
{"dataset": "StarLightCurves", "depth": 6, "nb_filters": 16, "batch_size": 32, "kernel_size": 32, "use_residual": "True", "use_bottleneck": "True", "acc": 0.9774162214667315, "precision": 0.9720479135847414, "recall": 0.9616647966278263, "budget_ran": 1500, "duration": 1240.8599128723145}
{"dataset": "StarLightCurves", "depth": 6, "nb_filters": 16, "batch_size": 32, "kernel_size": 41, "use_residual": "True", "use_bottleneck": "True", "acc": 0.977294803302574, "precision": 0.9712294164550416, "recall": 0.9618822664986683, "budget_ran": 1500, "duration": 1348.4967696666718}
{"dataset": "StarLightCurves", "depth": 6, "nb_filters": 16, "batch_size": 32, "kernel_size": 64, "use_residual": "True", "use_bottleneck": "True", "acc": 0.9776590577950461, "precision": 0.9687584012635501, "recall": 0.9662799088611176, "budget_ran": 1500, "duration": 1368.970913887024}
{"dataset": "StarLightCurves", "depth": 9, "nb_filters": 16, "batch_size": 32, "kernel_size": 41, "use_residual": "True", "use_bottleneck": "True", "acc": 0.9791160757649344, "precision": 0.9758688109474848, "recall": 0.9625823301685047, "budget_ran": 1500, "duration": 1934.1246666908264}
{"dataset": "StarLightCurves", "depth": 3, "nb_filters": 64, "batch_size": 128, "kernel_size": 41, "use_residual": "True", "use_bottleneck": "True", "acc": 0.9766877124817873, "precision": 0.9714274335096658, "recall": 0.9596138790553765, "budget_ran": 1500, "duration": 863.795902967453}
{"dataset": "StarLightCurves", "depth": 3, "nb_filters": 16, "batch_size": 64, "kernel_size": 41, "use_residual": "True", "use_bottleneck": "True", "acc": 0.9770519669742593, "precision": 0.9720951712713862, "recall": 0.9601759104633695, "budget_ran": 1500, "duration": 503.7590141296387}
{"dataset": "StarLightCurves", "depth": 6, "nb_filters": 16, "batch_size": 64, "kernel_size": 32, "use_residual": "True", "use_bottleneck": "True", "acc": 0.9777804759592035, "precision": 0.9744149840059825, "recall": 0.9600318370968214, "budget_ran": 1500, "duration": 865.372798204422}
{"dataset": "StarLightCurves", "depth": 6, "nb_filters": 16, "batch_size": 64, "kernel_size": 41, "use_residual": "True", "use_bottleneck": "True", "acc": 0.9789946576007771, "precision": 0.977540192627084, "recall": 0.9605199115314789, "budget_ran": 1500, "duration": 907.6574757099152}
{"dataset": "StarLightCurves", "depth": 6, "nb_filters": 16, "batch_size": 64, "kernel_size": 64, "use_residual": "True", "use_bottleneck": "True", "acc": 0.9798445847498786, "precision": 0.9759694219266034, "recall": 0.9647718404718394, "budget_ran": 1500, "duration": 925.5379836559296}
{"dataset": "StarLightCurves", "depth": 9, "nb_filters": 64, "batch_size": 32, "kernel_size": 41, "use_residual": "True", "use_bottleneck": "True", "acc": 0.9777804759592035, "precision": 0.974556382054761, "recall": 0.9598187475993515, "budget_ran": 1500, "duration": 3687.712241411209}
{"dataset": "StarLightCurves", "depth": 9, "nb_filters": 32, "batch_size": 32, "kernel_size": 64, "use_residual": "True", "use_bottleneck": "True", "acc": 0.976930548810102, "precision": 0.9729684567566389, "recall": 0.9590403465828077, "budget_ran": 1500, "duration": 2427.4305119514465}
{"dataset": "StarLightCurves", "depth": 9, "nb_filters": 16, "batch_size": 64, "kernel_size": 32, "use_residual": "True", "use_bottleneck": "True", "acc": 0.9730451675570665, "precision": 0.9652579518858643, "recall": 0.9553794922842966, "budget_ran": 1500, "duration": 1287.6158862113953}
{"dataset": "StarLightCurves", "depth": 9, "nb_filters": 64, "batch_size": 128, "kernel_size": 41, "use_residual": "True", "use_bottleneck": "True", "acc": 0.9766877124817873, "precision": 0.9728504274396036, "recall": 0.958260845303973, "budget_ran": 1500, "duration": 3147.7469387054443}
{"dataset": "StarLightCurves", "depth": 9, "nb_filters": 16, "batch_size": 64, "kernel_size": 41, "use_residual": "True", "use_bottleneck": "True", "acc": 0.9770519669742593, "precision": 0.9706735865724382, "recall": 0.9617420337122429, "budget_ran": 1500, "duration": 1407.8599376678467}
{"dataset": "StarLightCurves", "depth": 9, "nb_filters": 16, "batch_size": 64, "kernel_size": 64, "use_residual": "True", "use_bottleneck": "True", "acc": 0.9789946576007771, "precision": 0.9733137762877518, "recall": 0.9647817014808747, "budget_ran": 1500, "duration": 1459.89532995224}
{"dataset": "StarLightCurves", "depth": 6, "nb_filters": 16, "batch_size": 128, "kernel_size": 32, "use_residual": "True", "use_bottleneck": "True", "acc": 0.9777804759592035, "precision": 0.9756321156279576, "recall": 0.9592435750712424, "budget_ran": 1500, "duration": 685.9560513496399}
{"dataset": "StarLightCurves", "depth": 6, "nb_filters": 16, "batch_size": 128, "kernel_size": 41, "use_residual": "True", "use_bottleneck": "True", "acc": 0.9789946576007771, "precision": 0.9775627665346072, "recall": 0.9608715937598337, "budget_ran": 1500, "duration": 750.093775510788}
{"dataset": "StarLightCurves", "depth": 6, "nb_filters": 16, "batch_size": 128, "kernel_size": 64, "use_residual": "True", "use_bottleneck": "True", "acc": 0.977294803302574, "precision": 0.9716161734875022, "recall": 0.9614560875037288, "budget_ran": 1500, "duration": 805.980991601944}
{"dataset": "StarLightCurves", "depth": 9, "nb_filters": 16, "batch_size": 128, "kernel_size": 32, "use_residual": "True", "use_bottleneck": "True", "acc": 0.978630403108305, "precision": 0.977442859131825, "recall": 0.9593827075953767, "budget_ran": 1500, "duration": 1107.73033618927}
{"dataset": "StarLightCurves", "depth": 9, "nb_filters": 16, "batch_size": 128, "kernel_size": 41, "use_residual": "True", "use_bottleneck": "True", "acc": 0.9804516755706654, "precision": 0.9795764505046564, "recall": 0.9629915274632053, "budget_ran": 1500, "duration": 1168.1508626937866}
{"dataset": "StarLightCurves", "depth": 9, "nb_filters": 16, "batch_size": 128, "kernel_size": 64, "use_residual": "True", "use_bottleneck": "True", "acc": 0.9800874210781932, "precision": 0.9755191879202062, "recall": 0.9658389280147289, "budget_ran": 1500, "duration": 1288.0545568466187}
{"dataset": "StarLightCurves", "depth": 3, "nb_filters": 32, "batch_size": 16, "kernel_size": 32, "use_residual": "True", "use_bottleneck": "True", "acc": 0.9743807673627974, "precision": 0.9814103389429576, "recall": 0.9439301744872736, "budget_ran": 1500, "duration": 1407.1943378448486}
{"dataset": "StarLightCurves", "depth": 3, "nb_filters": 32, "batch_size": 16, "kernel_size": 41, "use_residual": "True", "use_bottleneck": "True", "acc": 0.9747450218552696, "precision": 0.9680828018940358, "recall": 0.9576396587740937, "budget_ran": 1500, "duration": 1437.785987854004}
{"dataset": "StarLightCurves", "depth": 3, "nb_filters": 32, "batch_size": 16, "kernel_size": 64, "use_residual": "True", "use_bottleneck": "True", "acc": 0.9763234579893152, "precision": 0.967554570231992, "recall": 0.9630260513327249, "budget_ran": 1500, "duration": 1535.1144707202911}
{"dataset": "StarLightCurves", "depth": 6, "nb_filters": 32, "batch_size": 16, "kernel_size": 32, "use_residual": "True", "use_bottleneck": "True", "acc": 0.9779018941233608, "precision": 0.9730974451937491, "recall": 0.9619452622006773, "budget_ran": 1500, "duration": 2396.3278138637543}
{"dataset": "StarLightCurves", "depth": 6, "nb_filters": 32, "batch_size": 16, "kernel_size": 41, "use_residual": "True", "use_bottleneck": "True", "acc": 0.9785089849441476, "precision": 0.9750006020425707, "recall": 0.9618696651718014, "budget_ran": 1500, "duration": 2601.587575674057}
{"dataset": "StarLightCurves", "depth": 6, "nb_filters": 32, "batch_size": 16, "kernel_size": 64, "use_residual": "True", "use_bottleneck": "True", "acc": 0.9783875667799903, "precision": 0.9743860859702712, "recall": 0.9622257277735283, "budget_ran": 1500, "duration": 2618.2798318862915}
{"dataset": "StarLightCurves", "depth": 9, "nb_filters": 32, "batch_size": 16, "kernel_size": 41, "use_residual": "True", "use_bottleneck": "True", "acc": 0.9781447304516756, "precision": 0.9744720257392209, "recall": 0.9612331369972237, "budget_ran": 1500, "duration": 3627.642364501953}
{"dataset": "StarLightCurves", "depth": 3, "nb_filters": 32, "batch_size": 32, "kernel_size": 41, "use_residual": "True", "use_bottleneck": "True", "acc": 0.9768091306459447, "precision": 0.9740428922694223, "recall": 0.9575531004738913, "budget_ran": 1500, "duration": 849.3209540843964}
{"dataset": "StarLightCurves", "depth": 6, "nb_filters": 32, "batch_size": 32, "kernel_size": 32, "use_residual": "True", "use_bottleneck": "True", "acc": 0.9780233122875183, "precision": 0.9727447890913474, "recall": 0.9628677365837692, "budget_ran": 1500, "duration": 1462.6340968608856}
{"dataset": "StarLightCurves", "depth": 6, "nb_filters": 32, "batch_size": 32, "kernel_size": 41, "use_residual": "True", "use_bottleneck": "True", "acc": 0.9775376396308888, "precision": 0.9734319690734113, "recall": 0.9603177833053355, "budget_ran": 1500, "duration": 1585.7821035385132}
{"dataset": "StarLightCurves", "depth": 6, "nb_filters": 32, "batch_size": 32, "kernel_size": 64, "use_residual": "True", "use_bottleneck": "True", "acc": 0.9781447304516756, "precision": 0.9733277269582418, "recall": 0.9622985844845725, "budget_ran": 1500, "duration": 1645.6668910980225}
{"dataset": "StarLightCurves", "depth": 9, "nb_filters": 32, "batch_size": 32, "kernel_size": 32, "use_residual": "True", "use_bottleneck": "True", "acc": 0.9762020398251579, "precision": 0.9710952806883039, "recall": 0.9591844199493561, "budget_ran": 1500, "duration": 2282.915961742401}
{"dataset": "StarLightCurves", "depth": 9, "nb_filters": 32, "batch_size": 32, "kernel_size": 41, "use_residual": "True", "use_bottleneck": "True", "acc": 0.9771733851384167, "precision": 0.9726537010095363, "recall": 0.9601074341256973, "budget_ran": 1500, "duration": 2332.015636205673}
{"dataset": "StarLightCurves", "depth": 3, "nb_filters": 32, "batch_size": 64, "kernel_size": 32, "use_residual": "True", "use_bottleneck": "True", "acc": 0.9768091306459447, "precision": 0.9753980447592122, "recall": 0.9562000667224878, "budget_ran": 1500, "duration": 564.3426160812378}
{"dataset": "StarLightCurves", "depth": 3, "nb_filters": 32, "batch_size": 64, "kernel_size": 41, "use_residual": "True", "use_bottleneck": "True", "acc": 0.9793589120932491, "precision": 0.9785926382769768, "recall": 0.960868853442002, "budget_ran": 1500, "duration": 582.0088691711426}
{"dataset": "StarLightCurves", "depth": 3, "nb_filters": 32, "batch_size": 64, "kernel_size": 64, "use_residual": "True", "use_bottleneck": "True", "acc": 0.9762020398251579, "precision": 0.9714404545619465, "recall": 0.9582679659951766, "budget_ran": 1500, "duration": 624.3127031326294}
{"dataset": "StarLightCurves", "depth": 6, "nb_filters": 32, "batch_size": 64, "kernel_size": 32, "use_residual": "True", "use_bottleneck": "True", "acc": 0.9788732394366197, "precision": 0.9777542211473155, "recall": 0.9600236161433265, "budget_ran": 1500, "duration": 1165.7368540763855}
{"dataset": "StarLightCurves", "depth": 6, "nb_filters": 32, "batch_size": 64, "kernel_size": 41, "use_residual": "True", "use_bottleneck": "True", "acc": 0.9785089849441476, "precision": 0.9736551479709373, "recall": 0.963222698923205, "budget_ran": 1500, "duration": 1219.8371295928955}
{"dataset": "StarLightCurves", "depth": 3, "nb_filters": 64, "batch_size": 32, "kernel_size": 41, "use_residual": "True", "use_bottleneck": "True", "acc": 0.9751092763477416, "precision": 0.9692502459929125, "recall": 0.9574879249230924, "budget_ran": 1500, "duration": 1163.9227030277252}
{"dataset": "StarLightCurves", "depth": 6, "nb_filters": 32, "batch_size": 64, "kernel_size": 64, "use_residual": "True", "use_bottleneck": "True", "acc": 0.9779018941233608, "precision": 0.9701600232070268, "recall": 0.9650030119318392, "budget_ran": 1500, "duration": 1255.2444171905518}
{"dataset": "StarLightCurves", "depth": 9, "nb_filters": 32, "batch_size": 64, "kernel_size": 32, "use_residual": "True", "use_bottleneck": "True", "acc": 0.9789946576007771, "precision": 0.9762687027752758, "recall": 0.9617984485162977, "budget_ran": 1500, "duration": 1767.8654508590698}
{"dataset": "StarLightCurves", "depth": 3, "nb_filters": 32, "batch_size": 128, "kernel_size": 41, "use_residual": "True", "use_bottleneck": "True", "acc": 0.9796017484215639, "precision": 0.9819637813469205, "recall": 0.9581003300304353, "budget_ran": 1500, "duration": 510.6845817565918}
{"dataset": "StarLightCurves", "depth": 6, "nb_filters": 32, "batch_size": 128, "kernel_size": 32, "use_residual": "True", "use_bottleneck": "True", "acc": 0.9794803302574066, "precision": 0.9784428528473511, "recall": 0.9612265560992693, "budget_ran": 1500, "duration": 1045.942176580429}
{"dataset": "StarLightCurves", "depth": 6, "nb_filters": 32, "batch_size": 128, "kernel_size": 41, "use_residual": "True", "use_bottleneck": "True", "acc": 0.9771733851384167, "precision": 0.9753448870487104, "recall": 0.95733727065859, "budget_ran": 1500, "duration": 1078.5014865398407}
{"dataset": "StarLightCurves", "depth": 6, "nb_filters": 32, "batch_size": 128, "kernel_size": 64, "use_residual": "True", "use_bottleneck": "True", "acc": 0.9777804759592035, "precision": 0.9727582709530985, "recall": 0.9618006490408798, "budget_ran": 1500, "duration": 1166.2716290950775}
{"dataset": "StarLightCurves", "depth": 9, "nb_filters": 32, "batch_size": 128, "kernel_size": 32, "use_residual": "True", "use_bottleneck": "True", "acc": 0.9787518212724624, "precision": 0.9792300905837537, "recall": 0.9583873765012404, "budget_ran": 1500, "duration": 1587.5906150341034}
{"dataset": "StarLightCurves", "depth": 9, "nb_filters": 32, "batch_size": 128, "kernel_size": 64, "use_residual": "True", "use_bottleneck": "True", "acc": 0.9753521126760564, "precision": 0.9664970661392386, "recall": 0.9613996726996739, "budget_ran": 1500, "duration": 1767.8378672599792}
{"dataset": "StarLightCurves", "depth": 3, "nb_filters": 64, "batch_size": 16, "kernel_size": 32, "use_residual": "True", "use_bottleneck": "True", "acc": 0.971830985915493, "precision": 0.960471228145188, "recall": 0.9573739950526918, "budget_ran": 1500, "duration": 1583.968889951706}
{"dataset": "StarLightCurves", "depth": 6, "nb_filters": 64, "batch_size": 16, "kernel_size": 32, "use_residual": "True", "use_bottleneck": "True", "acc": 0.9785089849441476, "precision": 0.9746709867903625, "recall": 0.9622958441667411, "budget_ran": 1500, "duration": 3041.4259538650513}
{"dataset": "StarLightCurves", "depth": 6, "nb_filters": 64, "batch_size": 16, "kernel_size": 41, "use_residual": "True", "use_bottleneck": "True", "acc": 0.9777804759592035, "precision": 0.9734901018161287, "recall": 0.9612358773150552, "budget_ran": 1500, "duration": 3094.2271065711975}
{"dataset": "StarLightCurves", "depth": 6, "nb_filters": 64, "batch_size": 16, "kernel_size": 64, "use_residual": "True", "use_bottleneck": "True", "acc": 0.9766877124817873, "precision": 0.9683842703951598, "recall": 0.9633749932432479, "budget_ran": 1500, "duration": 3236.233689546585}
{"dataset": "StarLightCurves", "depth": 9, "nb_filters": 64, "batch_size": 16, "kernel_size": 32, "use_residual": "True", "use_bottleneck": "True", "acc": 0.9777804759592035, "precision": 0.9751929802695439, "recall": 0.9593925686044119, "budget_ran": 1500, "duration": 4367.481273651123}
{"dataset": "StarLightCurves", "depth": 9, "nb_filters": 64, "batch_size": 16, "kernel_size": 41, "use_residual": "True", "use_bottleneck": "True", "acc": 0.9768091306459447, "precision": 0.9713082454383796, "recall": 0.9606749461693534, "budget_ran": 1500, "duration": 4707.621715545654}
{"dataset": "StarLightCurves", "depth": 9, "nb_filters": 64, "batch_size": 16, "kernel_size": 64, "use_residual": "True", "use_bottleneck": "True", "acc": 0.9776590577950461, "precision": 0.9707472283054565, "recall": 0.9637228348914801, "budget_ran": 1500, "duration": 4880.530945062637}
{"dataset": "StarLightCurves", "depth": 3, "nb_filters": 64, "batch_size": 32, "kernel_size": 64, "use_residual": "True", "use_bottleneck": "True", "acc": 0.976930548810102, "precision": 0.9727033244932821, "recall": 0.9594665255777474, "budget_ran": 1500, "duration": 1186.0923011302948}
{"dataset": "StarLightCurves", "depth": 6, "nb_filters": 64, "batch_size": 32, "kernel_size": 32, "use_residual": "True", "use_bottleneck": "True", "acc": 0.9759592034968432, "precision": 0.9689799163748477, "recall": 0.9606103104118038, "budget_ran": 1500, "duration": 2305.826691389084}
{"dataset": "StarLightCurves", "depth": 6, "nb_filters": 64, "batch_size": 32, "kernel_size": 41, "use_residual": "True", "use_bottleneck": "True", "acc": 0.9776590577950461, "precision": 0.9721002476285018, "recall": 0.9624442979066613, "budget_ran": 1500, "duration": 2418.89684343338}
{"dataset": "StarLightCurves", "depth": 6, "nb_filters": 64, "batch_size": 32, "kernel_size": 64, "use_residual": "True", "use_bottleneck": "True", "acc": 0.9751092763477416, "precision": 0.9661824513881468, "recall": 0.9613235358775487, "budget_ran": 1500, "duration": 2545.72216129303}
{"dataset": "StarLightCurves", "depth": 9, "nb_filters": 64, "batch_size": 32, "kernel_size": 32, "use_residual": "True", "use_bottleneck": "True", "acc": 0.976930548810102, "precision": 0.971495783949828, "recall": 0.9605319730650962, "budget_ran": 1500, "duration": 3523.595626592636}
{"dataset": "StarLightCurves", "depth": 3, "nb_filters": 64, "batch_size": 64, "kernel_size": 32, "use_residual": "True", "use_bottleneck": "True", "acc": 0.9766877124817873, "precision": 0.9746106979111339, "recall": 0.9566947220550995, "budget_ran": 1500, "duration": 924.0503084659576}
{"dataset": "StarLightCurves", "depth": 3, "nb_filters": 64, "batch_size": 64, "kernel_size": 41, "use_residual": "True", "use_bottleneck": "True", "acc": 0.9758377853326857, "precision": 0.9694791189365232, "recall": 0.9593361538003572, "budget_ran": 1500, "duration": 975.8755230903625}
{"dataset": "StarLightCurves", "depth": 6, "nb_filters": 64, "batch_size": 64, "kernel_size": 32, "use_residual": "True", "use_bottleneck": "True", "acc": 0.976930548810102, "precision": 0.9722249764623624, "recall": 0.9598927045726869, "budget_ran": 1500, "duration": 2005.997151374817}
{"dataset": "StarLightCurves", "depth": 6, "nb_filters": 64, "batch_size": 64, "kernel_size": 41, "use_residual": "True", "use_bottleneck": "True", "acc": 0.976930548810102, "precision": 0.9715711598064539, "recall": 0.9606064698316811, "budget_ran": 1500, "duration": 2087.4456417560577}
{"dataset": "StarLightCurves", "depth": 6, "nb_filters": 64, "batch_size": 64, "kernel_size": 64, "use_residual": "True", "use_bottleneck": "True", "acc": 0.9792374939290918, "precision": 0.9749533011331765, "recall": 0.9639950795108362, "budget_ran": 1500, "duration": 2246.3042719364166}
{"dataset": "StarLightCurves", "depth": 9, "nb_filters": 64, "batch_size": 64, "kernel_size": 41, "use_residual": "True", "use_bottleneck": "True", "acc": 0.9782661486158329, "precision": 0.9735034917477535, "recall": 0.9627948798727249, "budget_ran": 1500, "duration": 3224.4722640514374}
{"dataset": "StarLightCurves", "depth": 9, "nb_filters": 64, "batch_size": 64, "kernel_size": 64, "use_residual": "True", "use_bottleneck": "True", "acc": 0.9775376396308888, "precision": 0.9706603346604062, "recall": 0.9634396290007974, "budget_ran": 1500, "duration": 3447.811257839203}
{"dataset": "StarLightCurves", "depth": 3, "nb_filters": 64, "batch_size": 128, "kernel_size": 32, "use_residual": "True", "use_bottleneck": "True", "acc": 0.9771733851384167, "precision": 0.9725617443836477, "recall": 0.9598943446282274, "budget_ran": 1500, "duration": 862.6694688796997}
{"dataset": "StarLightCurves", "depth": 6, "nb_filters": 64, "batch_size": 128, "kernel_size": 32, "use_residual": "True", "use_bottleneck": "True", "acc": 0.9781447304516756, "precision": 0.9744381206373802, "recall": 0.9615848192255786, "budget_ran": 1500, "duration": 1885.772275686264}
{"dataset": "StarLightCurves", "depth": 6, "nb_filters": 64, "batch_size": 128, "kernel_size": 41, "use_residual": "True", "use_bottleneck": "True", "acc": 0.9783875667799903, "precision": 0.9775054612779311, "recall": 0.9586777030831266, "budget_ran": 1500, "duration": 2065.7305450439453}
{"dataset": "StarLightCurves", "depth": 6, "nb_filters": 64, "batch_size": 128, "kernel_size": 64, "use_residual": "True", "use_bottleneck": "True", "acc": 0.9791160757649344, "precision": 0.9764268279043306, "recall": 0.9620816544069801, "budget_ran": 1500, "duration": 2131.7371191978455}
{"dataset": "StarLightCurves", "depth": 9, "nb_filters": 64, "batch_size": 128, "kernel_size": 64, "use_residual": "True", "use_bottleneck": "True", "acc": 0.9788732394366197, "precision": 0.9761214960717758, "recall": 0.961515242625615, "budget_ran": 1500, "duration": 3327.80312871933}
{"dataset": "StarLightCurves", "depth": 3, "nb_filters": 16, "batch_size": 16, "kernel_size": 32, "use_residual": "True", "use_bottleneck": "False", "acc": 0.9749878581835842, "precision": 0.9677845552176635, "recall": 0.9584191600529285, "budget_ran": 1500, "duration": 1381.3862810134888}
{"dataset": "StarLightCurves", "depth": 3, "nb_filters": 16, "batch_size": 16, "kernel_size": 41, "use_residual": "True", "use_bottleneck": "False", "acc": 0.9738950947061681, "precision": 0.9665203202938869, "recall": 0.9567226650266649, "budget_ran": 1500, "duration": 1408.7656185626984}
{"dataset": "StarLightCurves", "depth": 3, "nb_filters": 16, "batch_size": 16, "kernel_size": 64, "use_residual": "True", "use_bottleneck": "False", "acc": 0.976930548810102, "precision": 0.9694884844283796, "recall": 0.962598772075494, "budget_ran": 1500, "duration": 1458.1912322044373}
{"dataset": "StarLightCurves", "depth": 6, "nb_filters": 16, "batch_size": 16, "kernel_size": 32, "use_residual": "True", "use_bottleneck": "False", "acc": 0.975594949004371, "precision": 0.9706329687106856, "recall": 0.9574912050341734, "budget_ran": 1500, "duration": 2314.3865010738373}
{"dataset": "StarLightCurves", "depth": 6, "nb_filters": 16, "batch_size": 16, "kernel_size": 41, "use_residual": "True", "use_bottleneck": "False", "acc": 0.9776590577950461, "precision": 0.9716011473827671, "recall": 0.9625932914398309, "budget_ran": 1500, "duration": 2335.4230692386627}
{"dataset": "StarLightCurves", "depth": 6, "nb_filters": 16, "batch_size": 16, "kernel_size": 64, "use_residual": "True", "use_bottleneck": "False", "acc": 0.9775376396308888, "precision": 0.9714360930818063, "recall": 0.9628003605083881, "budget_ran": 1500, "duration": 2608.7914876937866}
{"dataset": "StarLightCurves", "depth": 9, "nb_filters": 16, "batch_size": 16, "kernel_size": 32, "use_residual": "True", "use_bottleneck": "False", "acc": 0.9775376396308888, "precision": 0.9745219029639739, "recall": 0.9590392463205166, "budget_ran": 1500, "duration": 3252.1861639022827}
{"dataset": "StarLightCurves", "depth": 9, "nb_filters": 16, "batch_size": 16, "kernel_size": 41, "use_residual": "True", "use_bottleneck": "False", "acc": 0.973530840213696, "precision": 0.9621009509564082, "recall": 0.9606996090298378, "budget_ran": 1500, "duration": 3285.1301169395447}
{"dataset": "StarLightCurves", "depth": 9, "nb_filters": 16, "batch_size": 16, "kernel_size": 64, "use_residual": "True", "use_bottleneck": "False", "acc": 0.9783875667799903, "precision": 0.9708199366065413, "recall": 0.9659227459970996, "budget_ran": 1500, "duration": 3462.8248493671417}
{"dataset": "StarLightCurves", "depth": 3, "nb_filters": 16, "batch_size": 32, "kernel_size": 32, "use_residual": "True", "use_bottleneck": "False", "acc": 0.9757163671685284, "precision": 0.9806819857457084, "recall": 0.9486011617313701, "budget_ran": 1500, "duration": 758.3786211013794}
{"dataset": "StarLightCurves", "depth": 3, "nb_filters": 16, "batch_size": 32, "kernel_size": 41, "use_residual": "True", "use_bottleneck": "False", "acc": 0.9771733851384167, "precision": 0.9800045075044702, "recall": 0.9528623912117243, "budget_ran": 1500, "duration": 759.8426868915558}
{"dataset": "StarLightCurves", "depth": 3, "nb_filters": 16, "batch_size": 32, "kernel_size": 64, "use_residual": "True", "use_bottleneck": "False", "acc": 0.9765662943176299, "precision": 0.9683225713459639, "recall": 0.9629531946216804, "budget_ran": 1500, "duration": 751.9281446933746}
{"dataset": "StarLightCurves", "depth": 6, "nb_filters": 16, "batch_size": 32, "kernel_size": 32, "use_residual": "True", "use_bottleneck": "False", "acc": 0.98069451189898, "precision": 0.980026847864623, "recall": 0.9633448497471004, "budget_ran": 1500, "duration": 1262.3439855575562}
{"dataset": "StarLightCurves", "depth": 6, "nb_filters": 16, "batch_size": 32, "kernel_size": 41, "use_residual": "True", "use_bottleneck": "False", "acc": 0.9774162214667315, "precision": 0.9706665260940852, "recall": 0.9628047408817603, "budget_ran": 1500, "duration": 1358.1916105747223}
{"dataset": "StarLightCurves", "depth": 6, "nb_filters": 16, "batch_size": 32, "kernel_size": 64, "use_residual": "True", "use_bottleneck": "False", "acc": 0.9770519669742593, "precision": 0.9728498357923723, "recall": 0.9595366419709602, "budget_ran": 1500, "duration": 1395.9770045280457}
{"dataset": "StarLightCurves", "depth": 3, "nb_filters": 16, "batch_size": 128, "kernel_size": 41, "use_residual": "False", "use_bottleneck": "False", "acc": 0.9788732394366197, "precision": 0.9790731459143096, "recall": 0.9587450791585078, "budget_ran": 1500, "duration": 384.2700972557068}
{"dataset": "StarLightCurves", "depth": 9, "nb_filters": 16, "batch_size": 32, "kernel_size": 32, "use_residual": "True", "use_bottleneck": "False", "acc": 0.9775376396308888, "precision": 0.9729847712439684, "recall": 0.9608825550311599, "budget_ran": 1500, "duration": 1821.271485567093}
{"dataset": "StarLightCurves", "depth": 9, "nb_filters": 32, "batch_size": 16, "kernel_size": 32, "use_residual": "False", "use_bottleneck": "False", "acc": 0.9787518212724624, "precision": 0.9736116770303708, "recall": 0.9637891107045701, "budget_ran": 1500, "duration": 3340.300847530365}
{"dataset": "StarLightCurves", "depth": 9, "nb_filters": 16, "batch_size": 32, "kernel_size": 64, "use_residual": "True", "use_bottleneck": "False", "acc": 0.9787518212724624, "precision": 0.973808518905345, "recall": 0.9635760212071003, "budget_ran": 1500, "duration": 2016.2438662052155}
{"dataset": "StarLightCurves", "depth": 3, "nb_filters": 16, "batch_size": 64, "kernel_size": 64, "use_residual": "False", "use_bottleneck": "False", "acc": 0.9785089849441476, "precision": 0.9732500450087508, "recall": 0.9632867948875052, "budget_ran": 1500, "duration": 487.08829736709595}
{"dataset": "StarLightCurves", "depth": 3, "nb_filters": 64, "batch_size": 32, "kernel_size": 32, "use_residual": "False", "use_bottleneck": "False", "acc": 0.9764448761534725, "precision": 0.9745682395055032, "recall": 0.9558511248119647, "budget_ran": 1500, "duration": 1096.5581755638123}
{"dataset": "StarLightCurves", "depth": 3, "nb_filters": 16, "batch_size": 64, "kernel_size": 32, "use_residual": "True", "use_bottleneck": "False", "acc": 0.9675813501699855, "precision": 0.947898714427437, "recall": 0.9603216554935757, "budget_ran": 1500, "duration": 444.0390145778656}
{"dataset": "StarLightCurves", "depth": 9, "nb_filters": 32, "batch_size": 64, "kernel_size": 64, "use_residual": "False", "use_bottleneck": "False", "acc": 0.977294803302574, "precision": 0.9725214193264312, "recall": 0.9604651367829646, "budget_ran": 1500, "duration": 1947.3632292747498}
{"dataset": "StarLightCurves", "depth": 9, "nb_filters": 64, "batch_size": 32, "kernel_size": 64, "use_residual": "False", "use_bottleneck": "False", "acc": 0.9774162214667315, "precision": 0.9690777810099561, "recall": 0.9647225463589884, "budget_ran": 1500, "duration": 3884.9310064315796}
{"dataset": "StarLightCurves", "depth": 3, "nb_filters": 64, "batch_size": 64, "kernel_size": 64, "use_residual": "False", "use_bottleneck": "False", "acc": 0.9793589120932491, "precision": 0.9782091130298639, "recall": 0.9609433502085869, "budget_ran": 1500, "duration": 984.9560146331787}
{"dataset": "StarLightCurves", "depth": 3, "nb_filters": 16, "batch_size": 128, "kernel_size": 32, "use_residual": "False", "use_bottleneck": "False", "acc": 0.973530840213696, "precision": 0.9621785097693861, "recall": 0.9607741057964225, "budget_ran": 1500, "duration": 324.0283558368683}
{"dataset": "StarLightCurves", "depth": 3, "nb_filters": 64, "batch_size": 128, "kernel_size": 64, "use_residual": "False", "use_bottleneck": "False", "acc": 0.976930548810102, "precision": 0.9714940886355957, "recall": 0.9606064698316811, "budget_ran": 1500, "duration": 924.0053558349609}
{"dataset": "StarLightCurves", "depth": 3, "nb_filters": 16, "batch_size": 128, "kernel_size": 64, "use_residual": "False", "use_bottleneck": "False", "acc": 0.9781447304516756, "precision": 0.9746113595968429, "recall": 0.9610945442663388, "budget_ran": 1500, "duration": 384.1949484348297}
{"dataset": "StarLightCurves", "depth": 3, "nb_filters": 64, "batch_size": 16, "kernel_size": 41, "use_residual": "False", "use_bottleneck": "False", "acc": 0.9746236036911122, "precision": 0.9703533882447166, "recall": 0.9547993789137736, "budget_ran": 1500, "duration": 1646.1794350147247}
{"dataset": "StarLightCurves", "depth": 3, "nb_filters": 64, "batch_size": 16, "kernel_size": 64, "use_residual": "False", "use_bottleneck": "False", "acc": 0.9762020398251579, "precision": 0.9683941467455771, "recall": 0.9618159906855782, "budget_ran": 1500, "duration": 1692.7615826129913}
{"dataset": "StarLightCurves", "depth": 9, "nb_filters": 32, "batch_size": 64, "kernel_size": 41, "use_residual": "False", "use_bottleneck": "False", "acc": 0.976930548810102, "precision": 0.9698495491109721, "recall": 0.9624497785423244, "budget_ran": 1500, "duration": 1852.3979229927063}
{"dataset": "StarLightCurves", "depth": 3, "nb_filters": 32, "batch_size": 128, "kernel_size": 32, "use_residual": "False", "use_bottleneck": "False", "acc": 0.9770519669742593, "precision": 0.9718528711659266, "recall": 0.9607406821891941, "budget_ran": 1500, "duration": 463.9637475013733}
{"dataset": "StarLightCurves", "depth": 3, "nb_filters": 16, "batch_size": 64, "kernel_size": 41, "use_residual": "True", "use_bottleneck": "False", "acc": 0.9776590577950461, "precision": 0.9727777431925362, "recall": 0.9611657609218426, "budget_ran": 1500, "duration": 503.94785928726196}
{"dataset": "StarLightCurves", "depth": 3, "nb_filters": 16, "batch_size": 64, "kernel_size": 64, "use_residual": "True", "use_bottleneck": "False", "acc": 0.9789946576007771, "precision": 0.9793064333855698, "recall": 0.9589537882826056, "budget_ran": 1500, "duration": 503.80831837654114}
{"dataset": "StarLightCurves", "depth": 6, "nb_filters": 16, "batch_size": 64, "kernel_size": 32, "use_residual": "True", "use_bottleneck": "False", "acc": 0.9789946576007771, "precision": 0.9759443953103872, "recall": 0.9623632202421222, "budget_ran": 1500, "duration": 865.6615827083588}
{"dataset": "StarLightCurves", "depth": 9, "nb_filters": 64, "batch_size": 128, "kernel_size": 32, "use_residual": "False", "use_bottleneck": "False", "acc": 0.975230694511899, "precision": 0.9698863733413422, "recall": 0.9568546768595955, "budget_ran": 1500, "duration": 2826.437783241272}
{"dataset": "StarLightCurves", "depth": 9, "nb_filters": 32, "batch_size": 16, "kernel_size": 64, "use_residual": "False", "use_bottleneck": "False", "acc": 0.9768091306459447, "precision": 0.9682148609785711, "recall": 0.9639457853979851, "budget_ran": 1500, "duration": 3642.8935899734497}
{"dataset": "StarLightCurves", "depth": 3, "nb_filters": 32, "batch_size": 32, "kernel_size": 32, "use_residual": "False", "use_bottleneck": "False", "acc": 0.9780233122875183, "precision": 0.9775622693820077, "recall": 0.9576149959136093, "budget_ran": 1500, "duration": 784.7145698070526}
{"dataset": "StarLightCurves", "depth": 9, "nb_filters": 32, "batch_size": 128, "kernel_size": 41, "use_residual": "False", "use_bottleneck": "False", "acc": 0.9805730937348227, "precision": 0.9808117617749833, "recall": 0.961857603638184, "budget_ran": 1500, "duration": 1707.242404460907}
{"dataset": "StarLightCurves", "depth": 3, "nb_filters": 32, "batch_size": 128, "kernel_size": 64, "use_residual": "False", "use_bottleneck": "False", "acc": 0.9774162214667315, "precision": 0.9799105110046183, "recall": 0.9534288029930894, "budget_ran": 1500, "duration": 519.2050578594208}
{"dataset": "StarLightCurves", "depth": 9, "nb_filters": 64, "batch_size": 64, "kernel_size": 32, "use_residual": "False", "use_bottleneck": "False", "acc": 0.9765662943176299, "precision": 0.971496594386692, "recall": 0.9593306731646941, "budget_ran": 1500, "duration": 3087.543879032135}
{"dataset": "StarLightCurves", "depth": 6, "nb_filters": 16, "batch_size": 64, "kernel_size": 41, "use_residual": "True", "use_bottleneck": "False", "acc": 0.9787518212724624, "precision": 0.9751172795890827, "recall": 0.9627132624149365, "budget_ran": 1500, "duration": 905.7800772190094}
{"dataset": "StarLightCurves", "depth": 6, "nb_filters": 16, "batch_size": 64, "kernel_size": 64, "use_residual": "True", "use_bottleneck": "False", "acc": 0.9799660029140359, "precision": 0.976162535141219, "recall": 0.9647033641341672, "budget_ran": 1500, "duration": 925.7334167957306}
{"dataset": "StarLightCurves", "depth": 9, "nb_filters": 16, "batch_size": 64, "kernel_size": 32, "use_residual": "True", "use_bottleneck": "False", "acc": 0.9791160757649344, "precision": 0.9750695186636582, "recall": 0.9635732808892686, "budget_ran": 1500, "duration": 1226.9740481376648}
